dot_notate/__init__.py
dot_notate/dot.py
dot_notate/dot_notate.py
dict_dot_notate-0.0.3.dist-info/LICENSE
dict_dot_notate-0.0.3.dist-info/METADATA
dict_dot_notate-0.0.3.dist-info/WHEEL
dict_dot_notate-0.0.3.dist-info/top_level.txt
dict_dot_notate-0.0.3.dist-info/RECORD
