Metadata-Version: 2.1
Name: dict-dot-notate
Version: 0.0.3
Summary: Turns nested dictionary keys to dotted strings with their corresponding values into a basic dictionary
Home-page: https://github.com/kenneth051/dict-dot-notate
Author: Ddumba Kenneth
Author-email: kjdumba@gmail.com
License: UNKNOWN
Keywords: dict notate dictdot dot
Platform: UNKNOWN
Classifier: Development Status :: 5 - Production/Stable
Classifier: Intended Audience :: Developers
Classifier: Programming Language :: Python :: 3
Classifier: License :: OSI Approved :: MIT License
Classifier: Operating System :: OS Independent
Requires-Python: >=3
